blog_bridger_drf/__init__.py
blog_bridger_drf/admin.py
blog_bridger_drf/apps.py
blog_bridger_drf/default_settings.py
blog_bridger_drf/models.py
blog_bridger_drf/permissions.py
blog_bridger_drf/serializers.py
blog_bridger_drf/tests.py
blog_bridger_drf/urls.py
blog_bridger_drf/views.py
blog_bridger_drf/migrations/0001_initial.py
blog_bridger_drf/migrations/0002_comment_created_at_alter_post_author.py
blog_bridger_drf/migrations/0003_remove_comment_commenter_alter_comment_post.py
blog_bridger_drf/migrations/0004_comment_comment.py
blog_bridger_drf/migrations/0005_rename_author_comment_comment_author.py
blog_bridger_drf/migrations/0006_alter_post_options.py
blog_bridger_drf/migrations/0007_alter_comment_post.py
blog_bridger_drf/migrations/__init__.py
drf_blog_bridger-1.0.3.dist-info/LICENSE
drf_blog_bridger-1.0.3.dist-info/METADATA
drf_blog_bridger-1.0.3.dist-info/WHEEL
drf_blog_bridger-1.0.3.dist-info/top_level.txt
drf_blog_bridger-1.0.3.dist-info/RECORD
